deebot_t8/__init__.py
deebot_t8/api_client.py
deebot_t8/auth_client.py
deebot_t8/credentials.py
deebot_t8/entity.py
deebot_t8/exceptions.py
deebot_t8/md5.py
deebot_t8/portal_client.py
deebot_t8/subscription_client.py
deebot_t8/urls.py
deebot_t8/cli/__init__.py
deebot_t8/cli/__main__.py
deebot_t8/cli/config.py
deebot_t8-1.0.2.dist-info/LICENSE.txt
deebot_t8-1.0.2.dist-info/METADATA
deebot_t8-1.0.2.dist-info/WHEEL
deebot_t8-1.0.2.dist-info/entry_points.txt
deebot_t8-1.0.2.dist-info/top_level.txt
deebot_t8-1.0.2.dist-info/RECORD
