Metadata-Version: 2.1
Name: deebot-t8
Version: 1.0.2
Summary: Yet another Ecovacs Deebot API client
Home-page: https://github.com/nickw444/deebot-t8
Author: Nick Whyte
Author-email: nick@nickwhyte.com
License: UNKNOWN
Platform: UNKNOWN
Classifier: Intended Audience :: Developers
Classifier: Programming Language :: Python
License-File: LICENSE.txt
Requires-Dist: requests (<3.0.0,>=2.25.1)
Requires-Dist: paho-mqtt (<2.0.0,>=1.5.1)
Requires-Dist: dataclasses ; python_version < "3.7"
Provides-Extra: cli
Requires-Dist: click (<9.0.0,>=8.0.1) ; extra == 'cli'
Requires-Dist: terminaltables (<4.0.0,>=3.1.0) ; extra == 'cli'
